{
  "league_table": [
    {
      "id": 135855,
      "name": "Division 6C",
      "headings": {
        "column_1": "Team",
        "column_2": "p",
        "column_3": "w",
        "column_4": "t",
        "column_5": "l",
        "column_6": "a/c",
        "column_7": "wcn",
        "column_8": "lcn",
        "column_9": "BatP",
        "column_10": "BowlP",
        "column_11": "OffBP",
        "column_12": "Pen",
        "column_13": "Pts",
        "column_14": "AVE+"
      },
      "values": [
        {
          "position": "1",
          "team_id": "347205",
          "column_1": "Denham CC - 1st XI",
          "column_2": "0",
          "column_3": "0",
          "column_4": "0",
          "column_5": "0",
          "column_6": "0",
          "column_7": "0",
          "column_8": "0",
          "column_9": "0",
          "column_10": "0",
          "column_11": "0",
          "column_12": "0",
          "column_13": "0",
          "column_14": "0"
        },
        {
          "position": "2",
          "team_id": "22683",
          "column_1": "Amersham CC - 3rd XI",
          "column_2": "0",
          "column_3": "0",
          "column_4": "0",
          "column_5": "0",
          "column_6": "0",
          "column_7": "0",
          "column_8": "0",
          "column_9": "0",
          "column_10": "0",
          "column_11": "0",
          "column_12": "0",
          "column_13": "0",
          "column_14": "0"
        },
        {
          "position": "3",
          "team_id": "91926",
          "column_1": "High Wycombe CC - 4th XI",
          "column_2": "0",
          "column_3": "0",
          "column_4": "0",
          "column_5": "0",
          "column_6": "0",
          "column_7": "0",
          "column_8": "0",
          "column_9": "0",
          "column_10": "0",
          "column_11": "0",
          "column_12": "0",
          "column_13": "0",
          "column_14": "0"
        },
        {
          "position": "4",
          "team_id": "23025",
          "column_1": "Hurley CC - Saturday 2XI",
          "column_2": "0",
          "column_3": "0",
          "column_4": "0",
          "column_5": "0",
          "column_6": "0",
          "column_7": "0",
          "column_8": "0",
          "column_9": "0",
          "column_10": "0",
          "column_11": "0",
          "column_12": "0",
          "column_13": "0",
          "column_14": "0"
        },
        {
          "position": "5",
          "team_id": "12442",
          "column_1": "Maidenhead & Bray CC - 3rd XI",
          "column_2": "0",
          "column_3": "0",
          "column_4": "0",
          "column_5": "0",
          "column_6": "0",
          "column_7": "0",
          "column_8": "0",
          "column_9": "0",
          "column_10": "0",
          "column_11": "0",
          "column_12": "0",
          "column_13": "0",
          "column_14": "0"
        },
        {
          "position": "6",
          "team_id": "325395",
          "column_1": "Maidenhead Royals CC - 1st XI",
          "column_2": "0",
          "column_3": "0",
          "column_4": "0",
          "column_5": "0",
          "column_6": "0",
          "column_7": "0",
          "column_8": "0",
          "column_9": "0",
          "column_10": "0",
          "column_11": "0",
          "column_12": "0",
          "column_13": "0",
          "column_14": "0"
        },
        {
          "position": "7",
          "team_id": "33856",
          "column_1": "The Lee CC - 1st XI",
          "column_2": "0",
          "column_3": "0",
          "column_4": "0",
          "column_5": "0",
          "column_6": "0",
          "column_7": "0",
          "column_8": "0",
          "column_9": "0",
          "column_10": "0",
          "column_11": "0",
          "column_12": "0",
          "column_13": "0",
          "column_14": "0"
        },
        {
          "position": "8",
          "team_id": "123038",
          "column_1": "Tring Park CC - 3rd XI",
          "column_2": "0",
          "column_3": "0",
          "column_4": "0",
          "column_5": "0",
          "column_6": "0",
          "column_7": "0",
          "column_8": "0",
          "column_9": "0",
          "column_10": "0",
          "column_11": "0",
          "column_12": "0",
          "column_13": "0",
          "column_14": "0"
        },
        {
          "position": "9",
          "team_id": "171199",
          "column_1": "Wendover CC - 1st XI",
          "column_2": "0",
          "column_3": "0",
          "column_4": "0",
          "column_5": "0",
          "column_6": "0",
          "column_7": "0",
          "column_8": "0",
          "column_9": "0",
          "column_10": "0",
          "column_11": "0",
          "column_12": "0",
          "column_13": "0",
          "column_14": "0"
        },
        {
          "position": "10",
          "team_id": "34403",
          "column_1": "Wooburn Narkovians CC - 2nd XI",
          "column_2": "0",
          "column_3": "0",
          "column_4": "0",
          "column_5": "0",
          "column_6": "0",
          "column_7": "0",
          "column_8": "0",
          "column_9": "0",
          "column_10": "0",
          "column_11": "0",
          "column_12": "0",
          "column_13": "0",
          "column_14": "0"
        }
      ],
      "key": "p - Played,&nbsp;w - Won (22),&nbsp;t - Tied (14),&nbsp;l - Lost (0),&nbsp;a/c - Abandonned/Cancelled,&nbsp;wcn - Opposition Conceded (22),&nbsp;lcn - Team Conceded (0),&nbsp;BatP - Batting Bonus Points,&nbsp;BowlP - Bowling Bonus Points,&nbsp;OffBP - Officials Bonus Points,&nbsp;Pen - Penalty Points,&nbsp;Pts - Points,&nbsp;AVE+ - Average points all games"
    }
  ]
}